{"page": "VTV Th\u1ec3 Thao", "post_id": "669401871889216", "text": "Tr\u1ea7n Th\u1ecb Kim Thanh l\u1ecdt top 5 th\u1ee7 m\u00f4n xu\u1ea5t s\u1eafc nh\u1ea5t v\u00f2ng b\u1ea3ng World Cup 2023, do Sofascore th\u1ed1ng k\u00ea v\u00e0 b\u1ea7u ch\u1ecdn:\n\ud83d\udc49\ud83c\udffbTOP 2: C\u1ee9u thua (18 l\u1ea7n) & c\u1ea3n penalty (1 l\u1ea7n).\n\ud83d\udc49\ud83c\udffbTOP 4: \u0110i\u1ec3m s\u1ed1 t\u1eeb Sofascore (7,7 \u0111i\u1ec3m).\n\ud83d\udc49\ud83c\udffbTOP 5: C\u1ea3n ph\u00e1 c\u00fa s\u00fat trong v\u00f2ng c\u1ea5m (13 l\u1ea7n).", "timestamp": 1691204403, "likes": 0, "comments": 0}